Lopster
