Metadata-Version: 2.1
Name: Lopster
Version: 0.1.1
Summary: A simple shell for pygame. More info here https://github.com/Pinbib
Author: PinBib
Author-email: pinbib3@email.com
